redfetch/ResourceInstallBtn.js
redfetch/__about__.py
redfetch/__init__.py
redfetch/api.py
redfetch/auth.py
redfetch/config.py
redfetch/config_firstrun.py
redfetch/db.py
redfetch/detecteq.py
redfetch/download.py
redfetch/listener.py
redfetch/main.py
redfetch/meta.py
redfetch/push.py
redfetch/settings.toml
redfetch/terminal_ui.py
redfetch/terminal_ui.tcss
redfetch/unloadmq.py
redfetch/utils.py
redfetch-0.7.0.dist-info/METADATA
redfetch-0.7.0.dist-info/WHEEL
redfetch-0.7.0.dist-info/entry_points.txt
redfetch-0.7.0.dist-info/licenses/LICENSE
redfetch-0.7.0.dist-info/RECORD
