Metadata-Version: 2.4
Name: redfetch
Version: 0.7.0
Summary: Download and publish EverQuest scripts and software using the RedGuides API
Project-URL: Homepage, https://www.redguides.com
Project-URL: Documentation, https://www.redguides.com/community/resources/redfetch.3177/
Project-URL: Repository, https://github.com/RedGuides/redfetch
Project-URL: Issues, https://github.com/RedGuides/redfetch/issues
Project-URL: Changelog, https://github.com/RedGuides/redfetch/blob/main/CHANGELOG.md
Project-URL: Source_archive, https://github.com/RedGuides/redfetch/archive/a254b9e9c4171135554f2a50aca7aafd9ba44f71.zip
Author-email: Redbot <ask@redguides.com>
License-Expression: GPL-3.0-or-later
License-File: LICENSE
Classifier: Development Status :: 5 - Production/Stable
Classifier: Intended Audience :: End Users/Desktop
Classifier: License :: OSI Approved :: GNU General Public License v3 or later (GPLv3+)
Classifier: Operating System :: OS Independent
Classifier: Programming Language :: Python :: 3.12
Classifier: Topic :: Utilities
Requires-Dist: cheroot>=10.0.1
Requires-Dist: dynaconf>=3.2.6
Requires-Dist: flask-cors>=5.0.0
Requires-Dist: flask>=3.1.0
Requires-Dist: keepachangelog>=2.0.0
Requires-Dist: keyring>=25.5.0
Requires-Dist: md2bbcode
Requires-Dist: packaging>=24.2
Requires-Dist: platformdirs>=4.3.6
Requires-Dist: psutil>=6.1.0
Requires-Dist: pyperclip>=1.9.0
Requires-Dist: pywin32; sys_platform == 'win32'
Requires-Dist: requests>=2.32.3
Requires-Dist: rich-argparse>=1.6.0
Requires-Dist: rich>=13.9.4
Requires-Dist: textual-fspicker>=0.1.1
Requires-Dist: textual>=0.87.1
Requires-Dist: tomlkit>=0.13.2
